{"timestamp": "2025-05-03T12:14:03.536903", "event_type": "renames", "filename": "pagare_example.pdf", "folio": "3869525", "message": "Sucess"}
{"timestamp": "2025-05-03T12:16:32.534698", "event_type": "renames", "filename": "pagare_example.pdf", "folio": "3869525", "message": "Sucess"}
{"timestamp": "2025-05-03T12:19:12.761751", "event_type": "renames", "filename": "pagare_example.pdf", "folio": "3869525", "message": "Sucess"}
{"timestamp": "2025-05-03T12:29:57.373498", "event_type": "renames", "filename": "pagare_example.pdf", "folio": "3869525", "message": "Sucess"}
{"timestamp": "2025-05-03T12:31:36.570010", "event_type": "renames", "filename": "pagare_example.pdf", "folio": "3869525", "message": "Sucess"}
{"timestamp": "2025-05-03T12:34:49.998805", "event_type": "renames", "filename": "pagare_example.pdf", "folio": "3869525", "message": "Sucess"}
{"timestamp": "2025-05-03T13:47:18.575943", "event_type": "renames", "filename": "pagare_example.pdf", "folio": "3869525", "message": "Sucess"}
{"timestamp": "2025-05-03T13:51:18.376960", "event_type": "renames", "filename": "pagare_example.pdf", "folio": "3869525", "message": "Sucess"}
{"timestamp": "2025-05-03T13:51:48.586740", "event_type": "renames", "filename": "pagare_example.pdf", "folio": "3869525", "message": "Sucess"}
{"timestamp": "2025-05-04T10:26:48.588397", "event_type": "renames", "filename": "pagare_example.pdf", "folio": "3869525", "message": "Sucess"}
{"timestamp": "2025-05-04T23:30:19.057485", "event_type": "renames", "filename": "pagare_example.pdf", "folio": "3869525", "message": "Sucess"}
